{
  "The Odyssey (2D - English)": {
    "shows": 338,
    "venues": 74,
    "cities": 36,
    "totalSeats": 82044,
    "ticketsSold": 18124,
    "occupancy": 22.09,
    "grossRevenue": 3030414.5,
    "fastfilling": 58,
    "housefull": 0,
    "movieInfo": {}
  },
  "The Odyssey (2D - Hindi)": {
    "shows": 263,
    "venues": 81,
    "cities": 39,
    "totalSeats": 59645,
    "ticketsSold": 6519,
    "occupancy": 10.93,
    "grossRevenue": 1029931.66,
    "fastfilling": 11,
    "housefull": 0,
    "movieInfo": {}
  },
  "Dhamaal 4 (2D - Hindi)": {
    "shows": 698,
    "venues": 136,
    "cities": 72,
    "totalSeats": 145184,
    "ticketsSold": 20135,
    "occupancy": 13.87,
    "grossRevenue": 3196503.0,
    "fastfilling": 36,
    "housefull": 8,
    "movieInfo": {}
  },
  "Lenin (2D - Telugu)": {
    "shows": 110,
    "venues": 29,
    "cities": 25,
    "totalSeats": 33270,
    "ticketsSold": 2653,
    "occupancy": 7.97,
    "grossRevenue": 352322.0,
    "fastfilling": 1,
    "housefull": 0,
    "movieInfo": {}
  },
  "The Odyssey (2D - Telugu)": {
    "shows": 42,
    "venues": 10,
    "cities": 8,
    "totalSeats": 13831,
    "ticketsSold": 2436,
    "occupancy": 17.61,
    "grossRevenue": 338707.0,
    "fastfilling": 5,
    "housefull": 0,
    "movieInfo": {}
  },
  "The Odyssey (IMAX 2D - English)": {
    "shows": 5,
    "venues": 1,
    "cities": 1,
    "totalSeats": 1310,
    "ticketsSold": 996,
    "occupancy": 76.03,
    "grossRevenue": 905010.0,
    "fastfilling": 5,
    "housefull": 0,
    "movieInfo": {}
  },
  "Evil Dead Burn (2D - English)": {
    "shows": 70,
    "venues": 28,
    "cities": 15,
    "totalSeats": 12278,
    "ticketsSold": 1624,
    "occupancy": 13.23,
    "grossRevenue": 216337.0,
    "fastfilling": 4,
    "housefull": 0,
    "movieInfo": {}
  },
  "Alpha (2D - Hindi)": {
    "shows": 49,
    "venues": 33,
    "cities": 20,
    "totalSeats": 7119,
    "ticketsSold": 714,
    "occupancy": 10.03,
    "grossRevenue": 103084.0,
    "fastfilling": 0,
    "housefull": 0,
    "movieInfo": {}
  },
  "The Odyssey (4DX - English)": {
    "shows": 5,
    "venues": 1,
    "cities": 1,
    "totalSeats": 571,
    "ticketsSold": 494,
    "occupancy": 86.51,
    "grossRevenue": 172900.0,
    "fastfilling": 5,
    "housefull": 0,
    "movieInfo": {}
  },
  "Welcome To The Jungle (2D - Hindi)": {
    "shows": 53,
    "venues": 35,
    "cities": 18,
    "totalSeats": 11741,
    "ticketsSold": 2012,
    "occupancy": 17.14,
    "grossRevenue": 258680.0,
    "fastfilling": 3,
    "housefull": 0,
    "movieInfo": {}
  },
  "Evil Dead Burn (2D - Hindi)": {
    "shows": 62,
    "venues": 39,
    "cities": 18,
    "totalSeats": 11988,
    "ticketsSold": 2125,
    "occupancy": 17.73,
    "grossRevenue": 258576.0,
    "fastfilling": 5,
    "housefull": 1,
    "movieInfo": {}
  },
  "The Odyssey (DOLBY CINEMA 2D - English)": {
    "shows": 5,
    "venues": 1,
    "cities": 1,
    "totalSeats": 1545,
    "ticketsSold": 226,
    "occupancy": 14.63,
    "grossRevenue": 131750.0,
    "fastfilling": 0,
    "housefull": 0,
    "movieInfo": {}
  },
  "Idhayam Murali (2D - Tamil)": {
    "shows": 69,
    "venues": 23,
    "cities": 7,
    "totalSeats": 21546,
    "ticketsSold": 1650,
    "occupancy": 7.66,
    "grossRevenue": 209356.44,
    "fastfilling": 0,
    "housefull": 0,
    "movieInfo": {}
  },
  "The Odyssey (2D - Tamil)": {
    "shows": 34,
    "venues": 11,
    "cities": 4,
    "totalSeats": 10645,
    "ticketsSold": 1349,
    "occupancy": 12.67,
    "grossRevenue": 173619.48,
    "fastfilling": 2,
    "housefull": 0,
    "movieInfo": {}
  },
  "Gatta Kusthi 2 (2D - Tamil)": {
    "shows": 77,
    "venues": 24,
    "cities": 6,
    "totalSeats": 27251,
    "ticketsSold": 1766,
    "occupancy": 6.48,
    "grossRevenue": 237351.16,
    "fastfilling": 1,
    "housefull": 0,
    "movieInfo": {}
  },
  "Evil Dead Burn (2D - Tamil)": {
    "shows": 7,
    "venues": 5,
    "cities": 3,
    "totalSeats": 1762,
    "ticketsSold": 282,
    "occupancy": 16.0,
    "grossRevenue": 33135.84,
    "fastfilling": 0,
    "housefull": 0,
    "movieInfo": {}
  },
  "Evil Dead Burn (2D - Telugu)": {
    "shows": 3,
    "venues": 2,
    "cities": 2,
    "totalSeats": 879,
    "ticketsSold": 131,
    "occupancy": 14.9,
    "grossRevenue": 19852.0,
    "fastfilling": 0,
    "housefull": 0,
    "movieInfo": {}
  }
}