{
  "The Odyssey (2D - English)": {
    "shows": 113,
    "venues": 62,
    "cities": 28,
    "totalSeats": 28007,
    "ticketsSold": 4725,
    "occupancy": 16.87,
    "grossRevenue": 1209552.52,
    "fastfilling": 6,
    "housefull": 1,
    "movieInfo": {}
  },
  "Dhamaal 4 (2D - Hindi)": {
    "shows": 223,
    "venues": 128,
    "cities": 66,
    "totalSeats": 46429,
    "ticketsSold": 2856,
    "occupancy": 6.15,
    "grossRevenue": 593671.0,
    "fastfilling": 2,
    "housefull": 0,
    "movieInfo": {}
  },
  "The Odyssey (2D - Hindi)": {
    "shows": 101,
    "venues": 75,
    "cities": 36,
    "totalSeats": 23603,
    "ticketsSold": 2033,
    "occupancy": 8.61,
    "grossRevenue": 474668.0,
    "fastfilling": 0,
    "housefull": 1,
    "movieInfo": {}
  },
  "Koka Deuta Nati Aru Hati 2 (2D - Assamese)": {
    "shows": 3,
    "venues": 3,
    "cities": 3,
    "totalSeats": 490,
    "ticketsSold": 25,
    "occupancy": 5.1,
    "grossRevenue": 4110.0,
    "fastfilling": 0,
    "housefull": 0,
    "movieInfo": {}
  },
  "I, Nobody (2D - Malayalam)": {
    "shows": 4,
    "venues": 4,
    "cities": 4,
    "totalSeats": 527,
    "ticketsSold": 11,
    "occupancy": 2.09,
    "grossRevenue": 1548.5,
    "fastfilling": 0,
    "housefull": 0,
    "movieInfo": {}
  },
  "Varavu (2D - Malayalam)": {
    "shows": 24,
    "venues": 21,
    "cities": 12,
    "totalSeats": 6278,
    "ticketsSold": 620,
    "occupancy": 9.88,
    "grossRevenue": 94574.1,
    "fastfilling": 1,
    "housefull": 0,
    "movieInfo": {}
  },
  "Operation Aruna Reddy (2D - Telugu)": {
    "shows": 1,
    "venues": 1,
    "cities": 1,
    "totalSeats": 405,
    "ticketsSold": 0,
    "occupancy": 0.0,
    "grossRevenue": 0.0,
    "fastfilling": 0,
    "housefull": 0,
    "movieInfo": {}
  },
  "Mister Middle Class (2D - Telugu)": {
    "shows": 10,
    "venues": 9,
    "cities": 9,
    "totalSeats": 2313,
    "ticketsSold": 235,
    "occupancy": 10.16,
    "grossRevenue": 26206.0,
    "fastfilling": 1,
    "housefull": 0,
    "movieInfo": {}
  },
  "Oh..! Sukumari (2D - Telugu)": {
    "shows": 11,
    "venues": 11,
    "cities": 10,
    "totalSeats": 3412,
    "ticketsSold": 730,
    "occupancy": 21.4,
    "grossRevenue": 78811.0,
    "fastfilling": 1,
    "housefull": 0,
    "movieInfo": {}
  },
  "The Odyssey (2D - Telugu)": {
    "shows": 14,
    "venues": 10,
    "cities": 8,
    "totalSeats": 4287,
    "ticketsSold": 1214,
    "occupancy": 28.32,
    "grossRevenue": 186332.0,
    "fastfilling": 3,
    "housefull": 0,
    "movieInfo": {}
  },
  "Nagabandham - The Secret Treasure (2D - Hindi)": {
    "shows": 9,
    "venues": 9,
    "cities": 7,
    "totalSeats": 1764,
    "ticketsSold": 39,
    "occupancy": 2.21,
    "grossRevenue": 11190.0,
    "fastfilling": 0,
    "housefull": 0,
    "movieInfo": {}
  },
  "Oka Court Case (2D - Telugu)": {
    "shows": 1,
    "venues": 1,
    "cities": 1,
    "totalSeats": 368,
    "ticketsSold": 114,
    "occupancy": 30.98,
    "grossRevenue": 11970.0,
    "fastfilling": 0,
    "housefull": 0,
    "movieInfo": {}
  },
  "Lenin (2D - Telugu)": {
    "shows": 32,
    "venues": 27,
    "cities": 22,
    "totalSeats": 9250,
    "ticketsSold": 1040,
    "occupancy": 11.24,
    "grossRevenue": 126107.0,
    "fastfilling": 1,
    "housefull": 0,
    "movieInfo": {}
  },
  "Alpha (2D - Hindi)": {
    "shows": 25,
    "venues": 24,
    "cities": 14,
    "totalSeats": 4091,
    "ticketsSold": 204,
    "occupancy": 4.99,
    "grossRevenue": 47137.0,
    "fastfilling": 0,
    "housefull": 0,
    "movieInfo": {}
  },
  "Welcome To The Jungle (2D - Hindi)": {
    "shows": 21,
    "venues": 21,
    "cities": 12,
    "totalSeats": 3842,
    "ticketsSold": 540,
    "occupancy": 14.06,
    "grossRevenue": 77219.0,
    "fastfilling": 1,
    "housefull": 0,
    "movieInfo": {}
  },
  "Antappante Athbudha Pravarthikal (2D - Malayalam)": {
    "shows": 2,
    "venues": 2,
    "cities": 2,
    "totalSeats": 334,
    "ticketsSold": 0,
    "occupancy": 0.0,
    "grossRevenue": 0.0,
    "fastfilling": 0,
    "housefull": 0,
    "movieInfo": {}
  },
  "The Millet Diary (2D - Odia)": {
    "shows": 3,
    "venues": 3,
    "cities": 3,
    "totalSeats": 401,
    "ticketsSold": 19,
    "occupancy": 4.74,
    "grossRevenue": 3450.0,
    "fastfilling": 0,
    "housefull": 0,
    "movieInfo": {}
  },
  "Evil Dead Burn (2D - Hindi)": {
    "shows": 26,
    "venues": 24,
    "cities": 13,
    "totalSeats": 4850,
    "ticketsSold": 293,
    "occupancy": 6.04,
    "grossRevenue": 59013.0,
    "fastfilling": 0,
    "housefull": 0,
    "movieInfo": {}
  },
  "MRP (Neekentha Naakentha) (2D - Telugu)": {
    "shows": 4,
    "venues": 4,
    "cities": 4,
    "totalSeats": 1040,
    "ticketsSold": 157,
    "occupancy": 15.1,
    "grossRevenue": 14720.0,
    "fastfilling": 1,
    "housefull": 0,
    "movieInfo": {}
  },
  "Vadala (2D - Telugu)": {
    "shows": 4,
    "venues": 4,
    "cities": 3,
    "totalSeats": 1272,
    "ticketsSold": 109,
    "occupancy": 8.57,
    "grossRevenue": 11948.0,
    "fastfilling": 0,
    "housefull": 0,
    "movieInfo": {}
  },
  "Peddi (2D - Telugu)": {
    "shows": 2,
    "venues": 2,
    "cities": 2,
    "totalSeats": 656,
    "ticketsSold": 18,
    "occupancy": 2.74,
    "grossRevenue": 1800.0,
    "fastfilling": 0,
    "housefull": 0,
    "movieInfo": {}
  },
  "Evil Dead Burn (2D - English)": {
    "shows": 26,
    "venues": 21,
    "cities": 11,
    "totalSeats": 4501,
    "ticketsSold": 279,
    "occupancy": 6.2,
    "grossRevenue": 60049.0,
    "fastfilling": 0,
    "housefull": 0,
    "movieInfo": {}
  },
  "Achyuta Avataaram (2D - Malayalam)": {
    "shows": 8,
    "venues": 7,
    "cities": 5,
    "totalSeats": 2219,
    "ticketsSold": 87,
    "occupancy": 3.92,
    "grossRevenue": 12620.0,
    "fastfilling": 0,
    "housefull": 0,
    "movieInfo": {}
  },
  "Rakta Charitra (2D - Telugu)": {
    "shows": 1,
    "venues": 1,
    "cities": 1,
    "totalSeats": 236,
    "ticketsSold": 24,
    "occupancy": 10.17,
    "grossRevenue": 2400.0,
    "fastfilling": 0,
    "housefull": 0,
    "movieInfo": {}
  },
  "Cocktail 2 (2D - Hindi)": {
    "shows": 8,
    "venues": 6,
    "cities": 4,
    "totalSeats": 657,
    "ticketsSold": 30,
    "occupancy": 4.57,
    "grossRevenue": 6840.0,
    "fastfilling": 0,
    "housefull": 0,
    "movieInfo": {}
  },
  "The Odyssey (IMAX 2D - English)": {
    "shows": 2,
    "venues": 1,
    "cities": 1,
    "totalSeats": 524,
    "ticketsSold": 314,
    "occupancy": 59.92,
    "grossRevenue": 585300.0,
    "fastfilling": 2,
    "housefull": 0,
    "movieInfo": {}
  },
  "Anbe Diana (2D - Tamil)": {
    "shows": 20,
    "venues": 18,
    "cities": 9,
    "totalSeats": 5355,
    "ticketsSold": 379,
    "occupancy": 7.08,
    "grossRevenue": 43302.2,
    "fastfilling": 0,
    "housefull": 0,
    "movieInfo": {}
  },
  "Main Vaapas Aaunga (2D - Hindi)": {
    "shows": 4,
    "venues": 4,
    "cities": 2,
    "totalSeats": 611,
    "ticketsSold": 55,
    "occupancy": 9.0,
    "grossRevenue": 13810.0,
    "fastfilling": 0,
    "housefull": 0,
    "movieInfo": {}
  },
  "Toy Story 5 (3D - English)": {
    "shows": 1,
    "venues": 1,
    "cities": 1,
    "totalSeats": 104,
    "ticketsSold": 24,
    "occupancy": 23.08,
    "grossRevenue": 8400.0,
    "fastfilling": 0,
    "housefull": 0,
    "movieInfo": {}
  },
  "Idhayam Murali (2D - Tamil)": {
    "shows": 18,
    "venues": 17,
    "cities": 7,
    "totalSeats": 5006,
    "ticketsSold": 432,
    "occupancy": 8.63,
    "grossRevenue": 56047.74,
    "fastfilling": 0,
    "housefull": 0,
    "movieInfo": {}
  },
  "The Odyssey (4DX - English)": {
    "shows": 2,
    "venues": 1,
    "cities": 1,
    "totalSeats": 240,
    "ticketsSold": 136,
    "occupancy": 56.67,
    "grossRevenue": 101050.0,
    "fastfilling": 2,
    "housefull": 0,
    "movieInfo": {}
  },
  "Minions & Monsters (3D - English)": {
    "shows": 5,
    "venues": 5,
    "cities": 2,
    "totalSeats": 824,
    "ticketsSold": 26,
    "occupancy": 3.16,
    "grossRevenue": 6260.0,
    "fastfilling": 0,
    "housefull": 0,
    "movieInfo": {}
  },
  "Rahun Main Tere Rubaru (2D - Hindi)": {
    "shows": 2,
    "venues": 2,
    "cities": 2,
    "totalSeats": 434,
    "ticketsSold": 2,
    "occupancy": 0.46,
    "grossRevenue": 360.0,
    "fastfilling": 0,
    "housefull": 0,
    "movieInfo": {}
  },
  "Minions & Monsters (3D - Hindi)": {
    "shows": 1,
    "venues": 1,
    "cities": 1,
    "totalSeats": 67,
    "ticketsSold": 0,
    "occupancy": 0.0,
    "grossRevenue": 0.0,
    "fastfilling": 0,
    "housefull": 0,
    "movieInfo": {}
  },
  "Tumbadchi Manjula (2D - Marathi)": {
    "shows": 1,
    "venues": 1,
    "cities": 1,
    "totalSeats": 55,
    "ticketsSold": 4,
    "occupancy": 7.27,
    "grossRevenue": 760.0,
    "fastfilling": 0,
    "housefull": 0,
    "movieInfo": {}
  },
  "Deool Band 2 (2D - Marathi)": {
    "shows": 1,
    "venues": 1,
    "cities": 1,
    "totalSeats": 234,
    "ticketsSold": 40,
    "occupancy": 17.09,
    "grossRevenue": 8000.0,
    "fastfilling": 0,
    "housefull": 0,
    "movieInfo": {}
  },
  "The Odyssey (DOLBY CINEMA 2D - English)": {
    "shows": 2,
    "venues": 1,
    "cities": 1,
    "totalSeats": 618,
    "ticketsSold": 107,
    "occupancy": 17.31,
    "grossRevenue": 74250.0,
    "fastfilling": 0,
    "housefull": 0,
    "movieInfo": {}
  },
  "Ghabadkund (2D - Marathi)": {
    "shows": 1,
    "venues": 1,
    "cities": 1,
    "totalSeats": 241,
    "ticketsSold": 10,
    "occupancy": 4.15,
    "grossRevenue": 1980.0,
    "fastfilling": 0,
    "housefull": 0,
    "movieInfo": {}
  },
  "Moana (ICE 3D - English)": {
    "shows": 1,
    "venues": 1,
    "cities": 1,
    "totalSeats": 184,
    "ticketsSold": 14,
    "occupancy": 7.61,
    "grossRevenue": 6580.0,
    "fastfilling": 0,
    "housefull": 0,
    "movieInfo": {}
  },
  "Baby Do Die Do (2D - Hindi)": {
    "shows": 2,
    "venues": 2,
    "cities": 2,
    "totalSeats": 350,
    "ticketsSold": 12,
    "occupancy": 3.43,
    "grossRevenue": 7150.0,
    "fastfilling": 0,
    "housefull": 0,
    "movieInfo": {}
  },
  "Minions & Monsters (ICE 3D - English)": {
    "shows": 1,
    "venues": 1,
    "cities": 1,
    "totalSeats": 184,
    "ticketsSold": 21,
    "occupancy": 11.41,
    "grossRevenue": 10830.0,
    "fastfilling": 0,
    "housefull": 0,
    "movieInfo": {}
  },
  "Disclosure Day (2D - English)": {
    "shows": 1,
    "venues": 1,
    "cities": 1,
    "totalSeats": 25,
    "ticketsSold": 2,
    "occupancy": 8.0,
    "grossRevenue": 1400.0,
    "fastfilling": 0,
    "housefull": 0,
    "movieInfo": {}
  },
  "Graamaayana (2D - Kannada)": {
    "shows": 4,
    "venues": 2,
    "cities": 2,
    "totalSeats": 2772,
    "ticketsSold": 2,
    "occupancy": 0.07,
    "grossRevenue": 300.0,
    "fastfilling": 0,
    "housefull": 0,
    "movieInfo": {}
  },
  "Raja The Raja (2D - Telugu)": {
    "shows": 5,
    "venues": 5,
    "cities": 5,
    "totalSeats": 1792,
    "ticketsSold": 220,
    "occupancy": 12.28,
    "grossRevenue": 20294.0,
    "fastfilling": 0,
    "housefull": 0,
    "movieInfo": {}
  },
  "Arulvaan (2D - Tamil)": {
    "shows": 9,
    "venues": 8,
    "cities": 4,
    "totalSeats": 2499,
    "ticketsSold": 254,
    "occupancy": 10.16,
    "grossRevenue": 29536.8,
    "fastfilling": 0,
    "housefull": 0,
    "movieInfo": {}
  },
  "The Odyssey (2D - Tamil)": {
    "shows": 11,
    "venues": 9,
    "cities": 4,
    "totalSeats": 4486,
    "ticketsSold": 996,
    "occupancy": 22.2,
    "grossRevenue": 141957.88,
    "fastfilling": 0,
    "housefull": 1,
    "movieInfo": {}
  },
  "Gatta Kusthi 2 (2D - Tamil)": {
    "shows": 20,
    "venues": 19,
    "cities": 6,
    "totalSeats": 6654,
    "ticketsSold": 555,
    "occupancy": 8.34,
    "grossRevenue": 76663.9,
    "fastfilling": 0,
    "housefull": 0,
    "movieInfo": {}
  },
  "Sarpanch (2D - Punjabi)": {
    "shows": 7,
    "venues": 5,
    "cities": 3,
    "totalSeats": 1156,
    "ticketsSold": 106,
    "occupancy": 9.17,
    "grossRevenue": 22805.0,
    "fastfilling": 0,
    "housefull": 0,
    "movieInfo": {}
  },
  "Dastaar (2D - Punjabi)": {
    "shows": 30,
    "venues": 11,
    "cities": 6,
    "totalSeats": 5405,
    "ticketsSold": 353,
    "occupancy": 6.53,
    "grossRevenue": 75796.0,
    "fastfilling": 0,
    "housefull": 0,
    "movieInfo": {}
  },
  "Mein to Palavade Bandhi Preet (2D - Gujarati)": {
    "shows": 2,
    "venues": 2,
    "cities": 2,
    "totalSeats": 762,
    "ticketsSold": 0,
    "occupancy": 0.0,
    "grossRevenue": 0.0,
    "fastfilling": 0,
    "housefull": 0,
    "movieInfo": {}
  },
  "Peddi (2D - Hindi)": {
    "shows": 1,
    "venues": 1,
    "cities": 1,
    "totalSeats": 50,
    "ticketsSold": 0,
    "occupancy": 0.0,
    "grossRevenue": 0.0,
    "fastfilling": 0,
    "housefull": 0,
    "movieInfo": {}
  },
  "Ghatak (2D - Hindi)": {
    "shows": 1,
    "venues": 1,
    "cities": 1,
    "totalSeats": 80,
    "ticketsSold": 0,
    "occupancy": 0.0,
    "grossRevenue": 0.0,
    "fastfilling": 0,
    "housefull": 0,
    "movieInfo": {}
  },
  "Khalli Balli (2D - Hindi)": {
    "shows": 1,
    "venues": 1,
    "cities": 1,
    "totalSeats": 140,
    "ticketsSold": 0,
    "occupancy": 0.0,
    "grossRevenue": 0.0,
    "fastfilling": 0,
    "housefull": 0,
    "movieInfo": {}
  },
  "Abhhiman (2D - Bengali)": {
    "shows": 1,
    "venues": 1,
    "cities": 1,
    "totalSeats": 327,
    "ticketsSold": 6,
    "occupancy": 1.83,
    "grossRevenue": 1200.0,
    "fastfilling": 0,
    "housefull": 0,
    "movieInfo": {}
  },
  "Aajo Ardhangini (2D - Bengali)": {
    "shows": 3,
    "venues": 3,
    "cities": 2,
    "totalSeats": 704,
    "ticketsSold": 11,
    "occupancy": 1.56,
    "grossRevenue": 2700.0,
    "fastfilling": 0,
    "housefull": 0,
    "movieInfo": {}
  },
  "Haunted Echoes of the Past (2D - Hindi)": {
    "shows": 1,
    "venues": 1,
    "cities": 1,
    "totalSeats": 400,
    "ticketsSold": 0,
    "occupancy": 0.0,
    "grossRevenue": 0.0,
    "fastfilling": 0,
    "housefull": 0,
    "movieInfo": {}
  },
  "Achyuta Avataaram (2D - Kannada)": {
    "shows": 1,
    "venues": 1,
    "cities": 1,
    "totalSeats": 96,
    "ticketsSold": 0,
    "occupancy": 0.0,
    "grossRevenue": 0.0,
    "fastfilling": 0,
    "housefull": 0,
    "movieInfo": {}
  },
  "Mother Promise (2D - Kannada)": {
    "shows": 4,
    "venues": 3,
    "cities": 3,
    "totalSeats": 614,
    "ticketsSold": 17,
    "occupancy": 2.77,
    "grossRevenue": 2870.0,
    "fastfilling": 0,
    "housefull": 0,
    "movieInfo": {}
  },
  "Gajanana Cricketers Janthottu Since 1983 (2D - Tulu)": {
    "shows": 1,
    "venues": 1,
    "cities": 1,
    "totalSeats": 129,
    "ticketsSold": 0,
    "occupancy": 0.0,
    "grossRevenue": 0.0,
    "fastfilling": 0,
    "housefull": 0,
    "movieInfo": {}
  },
  "Carry on Jatta 4 (2D - Punjabi)": {
    "shows": 8,
    "venues": 6,
    "cities": 3,
    "totalSeats": 1069,
    "ticketsSold": 86,
    "occupancy": 8.04,
    "grossRevenue": 24863.0,
    "fastfilling": 0,
    "housefull": 0,
    "movieInfo": {}
  },
  "Hrudhayam Murali (2D - Telugu)": {
    "shows": 2,
    "venues": 2,
    "cities": 2,
    "totalSeats": 448,
    "ticketsSold": 7,
    "occupancy": 1.56,
    "grossRevenue": 1239.0,
    "fastfilling": 0,
    "housefull": 0,
    "movieInfo": {}
  },
  "Bara Badhu (2D - Odia)": {
    "shows": 2,
    "venues": 2,
    "cities": 2,
    "totalSeats": 190,
    "ticketsSold": 17,
    "occupancy": 8.95,
    "grossRevenue": 2550.0,
    "fastfilling": 0,
    "housefull": 0,
    "movieInfo": {}
  },
  "Ganda Bhairav (2D - Odia)": {
    "shows": 2,
    "venues": 2,
    "cities": 2,
    "totalSeats": 156,
    "ticketsSold": 0,
    "occupancy": 0.0,
    "grossRevenue": 0.0,
    "fastfilling": 0,
    "housefull": 0,
    "movieInfo": {}
  },
  "Dark (2026) (2D - Tamil)": {
    "shows": 1,
    "venues": 1,
    "cities": 1,
    "totalSeats": 333,
    "ticketsSold": 0,
    "occupancy": 0.0,
    "grossRevenue": 0.0,
    "fastfilling": 0,
    "housefull": 0,
    "movieInfo": {}
  },
  "Guruji Namaskar (2D - Odia)": {
    "shows": 1,
    "venues": 1,
    "cities": 1,
    "totalSeats": 86,
    "ticketsSold": 0,
    "occupancy": 0.0,
    "grossRevenue": 0.0,
    "fastfilling": 0,
    "housefull": 0,
    "movieInfo": {}
  },
  "The Invite (2D - English)": {
    "shows": 2,
    "venues": 2,
    "cities": 1,
    "totalSeats": 178,
    "ticketsSold": 9,
    "occupancy": 5.06,
    "grossRevenue": 3070.0,
    "fastfilling": 0,
    "housefull": 0,
    "movieInfo": {}
  },
  "Moana (3D - English)": {
    "shows": 4,
    "venues": 4,
    "cities": 1,
    "totalSeats": 636,
    "ticketsSold": 48,
    "occupancy": 7.55,
    "grossRevenue": 16270.0,
    "fastfilling": 0,
    "housefull": 0,
    "movieInfo": {}
  },
  "Moana (3D - Hindi)": {
    "shows": 2,
    "venues": 2,
    "cities": 2,
    "totalSeats": 243,
    "ticketsSold": 3,
    "occupancy": 1.23,
    "grossRevenue": 540.0,
    "fastfilling": 0,
    "housefull": 0,
    "movieInfo": {}
  },
  "Toy Story 5 (3D - Hindi)": {
    "shows": 1,
    "venues": 1,
    "cities": 1,
    "totalSeats": 67,
    "ticketsSold": 0,
    "occupancy": 0.0,
    "grossRevenue": 0.0,
    "fastfilling": 0,
    "housefull": 0,
    "movieInfo": {}
  },
  "Tula Pahta (2D - Marathi)": {
    "shows": 1,
    "venues": 1,
    "cities": 1,
    "totalSeats": 90,
    "ticketsSold": 83,
    "occupancy": 92.22,
    "grossRevenue": 12450.0,
    "fastfilling": 1,
    "housefull": 0,
    "movieInfo": {}
  },
  "Evil Dead Burn (2D - Tamil)": {
    "shows": 1,
    "venues": 1,
    "cities": 1,
    "totalSeats": 130,
    "ticketsSold": 13,
    "occupancy": 10.0,
    "grossRevenue": 1367.32,
    "fastfilling": 0,
    "housefull": 0,
    "movieInfo": {}
  },
  "Oh..! Sukumari (2D - Tamil)": {
    "shows": 3,
    "venues": 3,
    "cities": 2,
    "totalSeats": 1088,
    "ticketsSold": 37,
    "occupancy": 3.4,
    "grossRevenue": 3700.0,
    "fastfilling": 0,
    "housefull": 0,
    "movieInfo": {}
  },
  "Nagabandham - The Secret Treasure (2D - Telugu)": {
    "shows": 1,
    "venues": 1,
    "cities": 1,
    "totalSeats": 200,
    "ticketsSold": 0,
    "occupancy": 0.0,
    "grossRevenue": 0.0,
    "fastfilling": 0,
    "housefull": 0,
    "movieInfo": {}
  },
  "Mudharkanal (2D - Tamil)": {
    "shows": 1,
    "venues": 1,
    "cities": 1,
    "totalSeats": 222,
    "ticketsSold": 21,
    "occupancy": 9.46,
    "grossRevenue": 2100.0,
    "fastfilling": 0,
    "housefull": 0,
    "movieInfo": {}
  },
  "Balan: The Boy (2D - Malayalam)": {
    "shows": 1,
    "venues": 1,
    "cities": 1,
    "totalSeats": 205,
    "ticketsSold": 0,
    "occupancy": 0.0,
    "grossRevenue": 0.0,
    "fastfilling": 0,
    "housefull": 0,
    "movieInfo": {}
  },
  "Shikar (2D - Odia)": {
    "shows": 1,
    "venues": 1,
    "cities": 1,
    "totalSeats": 123,
    "ticketsSold": 0,
    "occupancy": 0.0,
    "grossRevenue": 0.0,
    "fastfilling": 0,
    "housefull": 0,
    "movieInfo": {}
  }
}