{
  "The Odyssey (2D - English)": {
    "shows": 589,
    "gross": 8512473.04,
    "sold": 28974,
    "totalSeats": 135032,
    "venues": 411,
    "cities": 100,
    "fastfilling": 62,
    "housefull": 3,
    "occupancy": 21.46,
    "movieInfo": {
      "contentId": 187151,
      "name": "The Odyssey",
      "lang": "English",
      "scrnFmt": "2D",
      "sndFmt": "",
      "censor": "A",
      "duration": 175,
      "genres": [
        "Adventure",
        "Epic"
      ],
      "poster": "https://cdn.district.in/movies-assets/images/cinema/THe-odyssey-3bc50d00-6288-11f1-a890-bfd3109fc6d5.jpg",
      "cover": "",
      "thumbnail": "",
      "trailer": "",
      "rating": {
        "hasUReview": 1,
        "imageUrl": "",
        "hasContent": 1
      },
      "isNew": false,
      "totalSessionCount": 2
    }
  },
  "Dhamaal 4 (2D - Hindi)": {
    "shows": 707,
    "gross": 2422843.71,
    "sold": 12064,
    "totalSeats": 144183,
    "venues": 585,
    "cities": 182,
    "fastfilling": 21,
    "housefull": 1,
    "occupancy": 8.37,
    "movieInfo": {
      "contentId": 206457,
      "name": "Dhamaal 4",
      "lang": "Hindi",
      "scrnFmt": "2D",
      "sndFmt": "",
      "censor": "UA13+",
      "duration": 143,
      "genres": [
        "Adventure",
        "Comedy"
      ],
      "poster": "https://b.zmtcdn.com/data/edition_assets/17836742758995427.jpg",
      "cover": "",
      "thumbnail": "",
      "trailer": "",
      "rating": {
        "hasUReview": 1,
        "imageUrl": "",
        "hasContent": 1
      },
      "isNew": false,
      "totalSessionCount": 4
    }
  },
  "The Odyssey (2D - Telugu)": {
    "shows": 15,
    "gross": 134497.0,
    "sold": 685,
    "totalSeats": 4210,
    "venues": 14,
    "cities": 8,
    "fastfilling": 0,
    "housefull": 0,
    "occupancy": 16.27,
    "movieInfo": {
      "contentId": 187151,
      "name": "The Odyssey",
      "lang": "English",
      "scrnFmt": "2D",
      "sndFmt": "",
      "censor": "A",
      "duration": 175,
      "genres": [
        "Adventure",
        "Epic"
      ],
      "poster": "https://cdn.district.in/movies-assets/images/cinema/THe-odyssey-3bc50d00-6288-11f1-a890-bfd3109fc6d5.jpg",
      "cover": "",
      "thumbnail": "",
      "trailer": "",
      "rating": {
        "hasUReview": 1,
        "imageUrl": "",
        "hasContent": 1
      },
      "isNew": false,
      "totalSessionCount": 2
    }
  },
  "Lenin (2D - Telugu)": {
    "shows": 52,
    "gross": 234375.36,
    "sold": 1089,
    "totalSeats": 10425,
    "venues": 52,
    "cities": 11,
    "fastfilling": 0,
    "housefull": 0,
    "occupancy": 10.45,
    "movieInfo": {
      "contentId": 195286,
      "name": "Lenin",
      "lang": "Telugu",
      "scrnFmt": "2D",
      "sndFmt": "",
      "censor": "UA16+",
      "duration": 158,
      "genres": [
        "Action"
      ],
      "poster": "https://cdn.district.in/movies-assets/images/cinema/poster_0004_Lenini-73309e00-1548-11f0-afe9-91710f201788-ba35f350-f769-11f0-9ad0-97f643f4852c.jpg",
      "cover": "",
      "thumbnail": "",
      "trailer": "https://www.youtube.com/watch?v=w2ZbnBobkuQ&t=2s",
      "rating": {
        "hasUReview": 0,
        "imageUrl": "",
        "hasContent": 1
      },
      "isNew": false,
      "totalSessionCount": 5
    }
  },
  "Evil Dead Burn (2D - Hindi)": {
    "shows": 131,
    "gross": 275512.03,
    "sold": 1346,
    "totalSeats": 24481,
    "venues": 131,
    "cities": 64,
    "fastfilling": 0,
    "housefull": 1,
    "occupancy": 5.5,
    "movieInfo": {
      "contentId": 207239,
      "name": "Evil Dead Burn",
      "lang": "Hindi",
      "scrnFmt": "2D",
      "sndFmt": "",
      "censor": "A",
      "duration": 112,
      "genres": [
        "Horror"
      ],
      "poster": "https://cdn.district.in/movies-assets/images/cinema/Evil-Dead-Burn_Poster-0eb5e430-49d1-11f1-a8aa-ef664b57e8ad-bcec1460-5e7c-11f1-bb0a-07766384fec6.jpg",
      "cover": "",
      "thumbnail": "",
      "trailer": "",
      "rating": {
        "hasUReview": 1,
        "imageUrl": "",
        "hasContent": 1
      },
      "isNew": false,
      "totalSessionCount": 1
    }
  },
  "The Odyssey (2D - Hindi)": {
    "shows": 345,
    "gross": 1396499.09,
    "sold": 6492,
    "totalSeats": 76741,
    "venues": 333,
    "cities": 130,
    "fastfilling": 5,
    "housefull": 1,
    "occupancy": 8.46,
    "movieInfo": {
      "contentId": 187151,
      "name": "The Odyssey",
      "lang": "English",
      "scrnFmt": "2D",
      "sndFmt": "",
      "censor": "A",
      "duration": 175,
      "genres": [
        "Adventure",
        "Epic"
      ],
      "poster": "https://cdn.district.in/movies-assets/images/cinema/THe-odyssey-3bc50d00-6288-11f1-a890-bfd3109fc6d5.jpg",
      "cover": "",
      "thumbnail": "",
      "trailer": "",
      "rating": {
        "hasUReview": 1,
        "imageUrl": "",
        "hasContent": 1
      },
      "isNew": false,
      "totalSessionCount": 4
    }
  },
  "Welcome To The Jungle (2D - Hindi)": {
    "shows": 64,
    "gross": 143193.0,
    "sold": 724,
    "totalSeats": 9532,
    "venues": 63,
    "cities": 30,
    "fastfilling": 2,
    "housefull": 1,
    "occupancy": 7.6,
    "movieInfo": {
      "contentId": 165834,
      "name": "Welcome To The Jungle",
      "lang": "Hindi",
      "scrnFmt": "2D",
      "sndFmt": "",
      "censor": "UA16+",
      "duration": 165,
      "genres": [
        "Action",
        "Drama",
        "Comedy"
      ],
      "poster": "https://cdn.district.in/movies-assets/images/cinema/17811549132914624-0667fb20-6dfc-11f1-9a9b-71d1ad62c0c2.jpg",
      "cover": "https://cdn.district.in/movies-assets/images/cinema/Welcome-To-The-Jungle-(Welcome-3)-73dfe610-d7c0-11ee-a5bd-f9e918a2ec60.jpg",
      "thumbnail": "",
      "trailer": "https://www.youtube.com/watch?v=L0L3GGgRMn0&ab_channel=JioStudios",
      "rating": {
        "hasUReview": 1,
        "imageUrl": "https://cdn.district.in/movies-assets/images/cinema/Welcome3-min-5ecae150-5064-11ee-9976-c32b18db04ad.jpg",
        "hasContent": 1
      },
      "isNew": false,
      "totalSessionCount": 3
    }
  },
  "Alpha (2D - Hindi)": {
    "shows": 47,
    "gross": 64130.0,
    "sold": 269,
    "totalSeats": 7089,
    "venues": 46,
    "cities": 29,
    "fastfilling": 0,
    "housefull": 0,
    "occupancy": 3.79,
    "movieInfo": {
      "contentId": 175697,
      "name": "Alpha",
      "lang": "Hindi",
      "scrnFmt": "2D",
      "sndFmt": "",
      "censor": "UA16+",
      "duration": 141,
      "genres": [
        "Action",
        "Thriller",
        "Spy"
      ],
      "poster": "https://cdn.district.in/movies-assets/images/cinema/Alpha-062ca980-6ef1-11f1-b0b5-2f04c00aa32d.jpg",
      "cover": "https://cdn.district.in/movies-assets/images/cinema/Alpha%20app-e0bcfb80-8254-11ef-98bc-d76cb3461e46.jpg",
      "thumbnail": "",
      "trailer": "",
      "rating": {
        "hasUReview": 1,
        "imageUrl": "",
        "hasContent": 1
      },
      "isNew": false,
      "totalSessionCount": 2
    }
  },
  "The Odyssey (4DX-2D - English)": {
    "shows": 36,
    "gross": 1253302.0,
    "sold": 1963,
    "totalSeats": 3496,
    "venues": 32,
    "cities": 18,
    "fastfilling": 20,
    "housefull": 3,
    "occupancy": 56.15,
    "movieInfo": {
      "contentId": 187151,
      "name": "The Odyssey",
      "lang": "English",
      "scrnFmt": "4DX-2D",
      "sndFmt": "",
      "censor": "A",
      "duration": 175,
      "genres": [
        "Adventure",
        "Epic"
      ],
      "poster": "https://cdn.district.in/movies-assets/images/cinema/THe-odyssey-poster-f81c2bf0-4852-11f1-ae93-11b250c87b8a-a9e46070-738f-11f1-b14c-c7bb4e91d5e6.jpg",
      "cover": "",
      "thumbnail": "",
      "trailer": "https://www.youtube.com/watch?v=xlPPOEWhxjI",
      "rating": {
        "hasUReview": 1,
        "imageUrl": "",
        "hasContent": 1
      },
      "isNew": false,
      "totalSessionCount": 5
    }
  },
  "The Odyssey (4DX-2D - Hindi)": {
    "shows": 1,
    "gross": 14950.0,
    "sold": 50,
    "totalSeats": 84,
    "venues": 1,
    "cities": 1,
    "fastfilling": 1,
    "housefull": 0,
    "occupancy": 59.52,
    "movieInfo": {
      "contentId": 187151,
      "name": "The Odyssey",
      "lang": "English",
      "scrnFmt": "4DX-2D",
      "sndFmt": "",
      "censor": "A",
      "duration": 175,
      "genres": [
        "Adventure",
        "Epic"
      ],
      "poster": "https://cdn.district.in/movies-assets/images/cinema/THe-odyssey-poster-f81c2bf0-4852-11f1-ae93-11b250c87b8a-a9e46070-738f-11f1-b14c-c7bb4e91d5e6.jpg",
      "cover": "",
      "thumbnail": "",
      "trailer": "https://www.youtube.com/watch?v=xlPPOEWhxjI",
      "rating": {
        "hasUReview": 1,
        "imageUrl": "",
        "hasContent": 1
      },
      "isNew": false,
      "totalSessionCount": 5
    }
  },
  "The Odyssey (IMAX 2D - English)": {
    "shows": 53,
    "gross": 16423317.96,
    "sold": 14929,
    "totalSeats": 18648,
    "venues": 32,
    "cities": 15,
    "fastfilling": 48,
    "housefull": 2,
    "occupancy": 80.06,
    "movieInfo": {
      "contentId": 187151,
      "name": "The Odyssey",
      "lang": "Hindi",
      "scrnFmt": "IMAX 2D",
      "sndFmt": "",
      "censor": "A",
      "duration": 175,
      "genres": [
        "Adventure",
        "Epic"
      ],
      "poster": "https://b.zmtcdn.com/data/edition_assets/17829803909946968.jpg",
      "cover": "",
      "thumbnail": "",
      "trailer": "",
      "rating": {
        "hasUReview": 1,
        "imageUrl": "",
        "hasContent": 1
      },
      "isNew": false,
      "totalSessionCount": 1
    }
  },
  "Evil Dead Burn (2D - English)": {
    "shows": 112,
    "gross": 316052.46,
    "sold": 1284,
    "totalSeats": 18731,
    "venues": 111,
    "cities": 38,
    "fastfilling": 2,
    "housefull": 0,
    "occupancy": 6.85,
    "movieInfo": {
      "contentId": 207239,
      "name": "Evil Dead Burn",
      "lang": "English",
      "scrnFmt": "2D",
      "sndFmt": "",
      "censor": "A",
      "duration": 112,
      "genres": [
        "Horror"
      ],
      "poster": "https://b.zmtcdn.com/data/edition_assets/17833362123847753.jpg",
      "cover": "",
      "thumbnail": "",
      "trailer": "",
      "rating": {
        "hasUReview": 1,
        "imageUrl": "",
        "hasContent": 1
      },
      "isNew": false,
      "totalSessionCount": 1
    }
  },
  "Idhayam Murali (2D - Tamil)": {
    "shows": 40,
    "gross": 377146.45,
    "sold": 2425,
    "totalSeats": 10164,
    "venues": 39,
    "cities": 10,
    "fastfilling": 1,
    "housefull": 0,
    "occupancy": 23.86,
    "movieInfo": {
      "contentId": 190425,
      "name": "Idhayam Murali",
      "lang": "Tamil",
      "scrnFmt": "2D",
      "sndFmt": "",
      "censor": "UA13+",
      "duration": 166,
      "genres": [
        "Drama",
        "Romance"
      ],
      "poster": "https://cdn.district.in/movies-assets/images/cinema/Idhayam-Murali-6637f280-5f24-11f1-b98c-2f82e8f1e34c.jpg",
      "cover": "",
      "thumbnail": "",
      "trailer": "https://www.youtube.com/watch?v=TLFPhWGEhKA&list=RDTLFPhWGEhKA&start_radio=1",
      "rating": {
        "hasUReview": 1,
        "imageUrl": "",
        "hasContent": 1
      },
      "isNew": false,
      "totalSessionCount": 4
    }
  },
  "Gatta Kusthi 2 (2D - Tamil)": {
    "shows": 17,
    "gross": 175596.8,
    "sold": 1211,
    "totalSeats": 4716,
    "venues": 17,
    "cities": 9,
    "fastfilling": 1,
    "housefull": 0,
    "occupancy": 25.68,
    "movieInfo": {
      "contentId": 205464,
      "name": "Gatta Kusthi 2",
      "lang": "Tamil",
      "scrnFmt": "2D",
      "sndFmt": "",
      "censor": "U",
      "duration": 154,
      "genres": [
        "Sport",
        "Drama",
        "Romance",
        "Comedy"
      ],
      "poster": "https://cdn.district.in/movies-assets/images/cinema/Gatta%20K-c35dfec0-5f22-11f1-9cda-6dc343c00fe2.jpg",
      "cover": "",
      "thumbnail": "",
      "trailer": "https://www.youtube.com/watch?v=cc8FDOConV0",
      "rating": {
        "hasUReview": 0,
        "imageUrl": "",
        "hasContent": 1
      },
      "isNew": false,
      "totalSessionCount": 2
    }
  },
  "The Odyssey (MX4D - English)": {
    "shows": 3,
    "gross": 91050.0,
    "sold": 149,
    "totalSeats": 256,
    "venues": 2,
    "cities": 2,
    "fastfilling": 2,
    "housefull": 0,
    "occupancy": 58.2,
    "movieInfo": {
      "contentId": 187151,
      "name": "The Odyssey",
      "lang": "English",
      "scrnFmt": "MX4D",
      "sndFmt": "",
      "censor": "A",
      "duration": 175,
      "genres": [
        "Adventure",
        "Epic"
      ],
      "poster": "https://b.zmtcdn.com/data/edition_assets/17828122685871582.jpg",
      "cover": "",
      "thumbnail": "",
      "trailer": "",
      "rating": {
        "hasUReview": 1,
        "imageUrl": "",
        "hasContent": 1
      },
      "isNew": false,
      "totalSessionCount": 5
    }
  },
  "Evil Dead Burn (2D - Tamil)": {
    "shows": 16,
    "gross": 73560.65,
    "sold": 603,
    "totalSeats": 3413,
    "venues": 16,
    "cities": 3,
    "fastfilling": 0,
    "housefull": 0,
    "occupancy": 17.67,
    "movieInfo": {
      "contentId": 207239,
      "name": "Evil Dead Burn",
      "lang": "Tamil",
      "scrnFmt": "2D",
      "sndFmt": "",
      "censor": "A",
      "duration": 112,
      "genres": [
        "Horror"
      ],
      "poster": "https://cdn.district.in/movies-assets/images/cinema/Evil-Dead-Burn_Poster-0eb5e430-49d1-11f1-a8aa-ef664b57e8ad-05720f00-5e7d-11f1-abbc-57776f320c87.jpg",
      "cover": "",
      "thumbnail": "",
      "trailer": "",
      "rating": {
        "hasUReview": 1,
        "imageUrl": "",
        "hasContent": 1
      },
      "isNew": false,
      "totalSessionCount": 2
    }
  },
  "The Odyssey (2D - Tamil)": {
    "shows": 19,
    "gross": 176190.9,
    "sold": 1259,
    "totalSeats": 4933,
    "venues": 19,
    "cities": 5,
    "fastfilling": 1,
    "housefull": 0,
    "occupancy": 25.52,
    "movieInfo": {
      "contentId": 187151,
      "name": "The Odyssey",
      "lang": "Tamil",
      "scrnFmt": "2D",
      "sndFmt": "",
      "censor": "A",
      "duration": 175,
      "genres": [
        "Adventure",
        "Epic"
      ],
      "poster": "https://cdn.district.in/movies-assets/images/cinema/THe-odyssey-8dba09d0-6288-11f1-9f5b-8fefdf83467e.jpg",
      "cover": "",
      "thumbnail": "",
      "trailer": "https://www.youtube.com/watch?v=JLEDwlSZcAI",
      "rating": {
        "hasUReview": 1,
        "imageUrl": "",
        "hasContent": 1
      },
      "isNew": false,
      "totalSessionCount": 3
    }
  },
  "The Odyssey (MX4D - Hindi)": {
    "shows": 1,
    "gross": 34900.0,
    "sold": 80,
    "totalSeats": 135,
    "venues": 1,
    "cities": 1,
    "fastfilling": 1,
    "housefull": 0,
    "occupancy": 59.26,
    "movieInfo": {
      "contentId": 187151,
      "name": "The Odyssey",
      "lang": "Hindi",
      "scrnFmt": "MX4D",
      "sndFmt": "",
      "censor": "A",
      "duration": 175,
      "genres": [
        "Adventure",
        "Epic"
      ],
      "poster": "https://b.zmtcdn.com/data/edition_assets/17836789678012830.jpg",
      "cover": "",
      "thumbnail": "",
      "trailer": "",
      "rating": {
        "hasUReview": 1,
        "imageUrl": "",
        "hasContent": 1
      },
      "isNew": false,
      "totalSessionCount": 2
    }
  }
}