{
  "Dhamaal 4 (2D - Hindi)": {
    "shows": 960,
    "venues": 240,
    "cities": 105,
    "totalSeats": 198806,
    "ticketsSold": 22775,
    "occupancy": 11.46,
    "grossRevenue": 4135822.92,
    "fastfilling": 21,
    "housefull": 3,
    "movieInfo": {}
  },
  "I, Nobody (2D - Malayalam)": {
    "shows": 41,
    "venues": 24,
    "cities": 18,
    "totalSeats": 10527,
    "ticketsSold": 281,
    "occupancy": 2.67,
    "grossRevenue": 43359.4,
    "fastfilling": 0,
    "housefull": 0,
    "movieInfo": {}
  },
  "Alpha (2D - Hindi)": {
    "shows": 213,
    "venues": 143,
    "cities": 60,
    "totalSeats": 33068,
    "ticketsSold": 2681,
    "occupancy": 8.11,
    "grossRevenue": 381391.0,
    "fastfilling": 2,
    "housefull": 0,
    "movieInfo": {}
  },
  "Nagabandham - The Secret Treasure (2D - Telugu)": {
    "shows": 26,
    "venues": 15,
    "cities": 15,
    "totalSeats": 9666,
    "ticketsSold": 1455,
    "occupancy": 15.05,
    "grossRevenue": 137157.0,
    "fastfilling": 1,
    "housefull": 2,
    "movieInfo": {}
  },
  "Lenin (2D - Telugu)": {
    "shows": 74,
    "venues": 39,
    "cities": 36,
    "totalSeats": 24057,
    "ticketsSold": 4605,
    "occupancy": 19.14,
    "grossRevenue": 559059.0,
    "fastfilling": 2,
    "housefull": 0,
    "movieInfo": {}
  },
  "Peddi (2D - Telugu)": {
    "shows": 8,
    "venues": 4,
    "cities": 4,
    "totalSeats": 2452,
    "ticketsSold": 121,
    "occupancy": 4.93,
    "grossRevenue": 13480.0,
    "fastfilling": 0,
    "housefull": 0,
    "movieInfo": {}
  },
  "Main Vaapas Aaunga (2D - Hindi)": {
    "shows": 32,
    "venues": 29,
    "cities": 14,
    "totalSeats": 5080,
    "ticketsSold": 988,
    "occupancy": 19.45,
    "grossRevenue": 140157.84,
    "fastfilling": 2,
    "housefull": 0,
    "movieInfo": {}
  },
  "Evil Dead Burn (2D - Hindi)": {
    "shows": 148,
    "venues": 99,
    "cities": 40,
    "totalSeats": 29552,
    "ticketsSold": 4735,
    "occupancy": 16.02,
    "grossRevenue": 559923.0,
    "fastfilling": 10,
    "housefull": 4,
    "movieInfo": {}
  },
  "Aajo Ardhangini (2D - Bengali)": {
    "shows": 6,
    "venues": 6,
    "cities": 3,
    "totalSeats": 963,
    "ticketsSold": 143,
    "occupancy": 14.85,
    "grossRevenue": 25795.0,
    "fastfilling": 0,
    "housefull": 0,
    "movieInfo": {}
  },
  "Welcome To The Jungle (2D - Hindi)": {
    "shows": 200,
    "venues": 132,
    "cities": 48,
    "totalSeats": 30205,
    "ticketsSold": 2915,
    "occupancy": 9.65,
    "grossRevenue": 390275.0,
    "fastfilling": 4,
    "housefull": 0,
    "movieInfo": {}
  },
  "Vasudheva Sutham (2D - Telugu)": {
    "shows": 9,
    "venues": 5,
    "cities": 5,
    "totalSeats": 2365,
    "ticketsSold": 17,
    "occupancy": 0.72,
    "grossRevenue": 3250.0,
    "fastfilling": 0,
    "housefull": 0,
    "movieInfo": {}
  },
  "Boys Never Compromise (2D - Kannada)": {
    "shows": 7,
    "venues": 4,
    "cities": 4,
    "totalSeats": 3083,
    "ticketsSold": 58,
    "occupancy": 1.88,
    "grossRevenue": 6820.0,
    "fastfilling": 0,
    "housefull": 0,
    "movieInfo": {}
  },
  "Carry on Jatta 4 (2D - Punjabi)": {
    "shows": 42,
    "venues": 23,
    "cities": 14,
    "totalSeats": 7112,
    "ticketsSold": 542,
    "occupancy": 7.62,
    "grossRevenue": 56549.0,
    "fastfilling": 0,
    "housefull": 0,
    "movieInfo": {}
  },
  "Evil Dead Burn (2D - Telugu)": {
    "shows": 20,
    "venues": 11,
    "cities": 11,
    "totalSeats": 7880,
    "ticketsSold": 1391,
    "occupancy": 17.65,
    "grossRevenue": 133780.0,
    "fastfilling": 0,
    "housefull": 2,
    "movieInfo": {}
  },
  "Guruji Namaskar (2D - Odia)": {
    "shows": 4,
    "venues": 4,
    "cities": 4,
    "totalSeats": 224,
    "ticketsSold": 19,
    "occupancy": 8.48,
    "grossRevenue": 5098.0,
    "fastfilling": 0,
    "housefull": 0,
    "movieInfo": {}
  },
  "Moana (3D - Hindi)": {
    "shows": 41,
    "venues": 35,
    "cities": 18,
    "totalSeats": 7406,
    "ticketsSold": 562,
    "occupancy": 7.59,
    "grossRevenue": 89801.0,
    "fastfilling": 0,
    "housefull": 1,
    "movieInfo": {}
  },
  "Nagabandham - The Secret Treasure (2D - Hindi)": {
    "shows": 16,
    "venues": 14,
    "cities": 10,
    "totalSeats": 1790,
    "ticketsSold": 272,
    "occupancy": 15.2,
    "grossRevenue": 47596.0,
    "fastfilling": 1,
    "housefull": 0,
    "movieInfo": {}
  },
  "Jindagi Once More (2D - Gujarati)": {
    "shows": 14,
    "venues": 11,
    "cities": 2,
    "totalSeats": 1344,
    "ticketsSold": 229,
    "occupancy": 17.04,
    "grossRevenue": 28670.0,
    "fastfilling": 2,
    "housefull": 0,
    "movieInfo": {}
  },
  "Cocktail 2 (2D - Hindi)": {
    "shows": 19,
    "venues": 14,
    "cities": 5,
    "totalSeats": 2127,
    "ticketsSold": 361,
    "occupancy": 16.97,
    "grossRevenue": 58763.0,
    "fastfilling": 0,
    "housefull": 0,
    "movieInfo": {}
  },
  "State of Ramadhani: Dharyu Dhani Nu Thay (2D - Gujarati)": {
    "shows": 9,
    "venues": 7,
    "cities": 3,
    "totalSeats": 1277,
    "ticketsSold": 106,
    "occupancy": 8.3,
    "grossRevenue": 11939.0,
    "fastfilling": 0,
    "housefull": 0,
    "movieInfo": {}
  },
  "Evil Dead Burn (2D - English)": {
    "shows": 46,
    "venues": 36,
    "cities": 25,
    "totalSeats": 7906,
    "ticketsSold": 1257,
    "occupancy": 15.9,
    "grossRevenue": 200219.3,
    "fastfilling": 4,
    "housefull": 0,
    "movieInfo": {}
  },
  "Sarpanch (2D - Punjabi)": {
    "shows": 48,
    "venues": 23,
    "cities": 15,
    "totalSeats": 6754,
    "ticketsSold": 312,
    "occupancy": 4.62,
    "grossRevenue": 37134.0,
    "fastfilling": 0,
    "housefull": 0,
    "movieInfo": {}
  },
  "Gatta Kusthi 2 (2D - Tamil)": {
    "shows": 73,
    "venues": 37,
    "cities": 11,
    "totalSeats": 25390,
    "ticketsSold": 2236,
    "occupancy": 8.81,
    "grossRevenue": 328308.39,
    "fastfilling": 0,
    "housefull": 0,
    "movieInfo": {}
  },
  "Idhayam Murali (2D - Tamil)": {
    "shows": 82,
    "venues": 35,
    "cities": 12,
    "totalSeats": 27831,
    "ticketsSold": 3523,
    "occupancy": 12.66,
    "grossRevenue": 533150.93,
    "fastfilling": 3,
    "housefull": 0,
    "movieInfo": {}
  },
  "Evil Dead Burn (2D - Tamil)": {
    "shows": 24,
    "venues": 16,
    "cities": 5,
    "totalSeats": 6180,
    "ticketsSold": 933,
    "occupancy": 15.1,
    "grossRevenue": 129709.3,
    "fastfilling": 1,
    "housefull": 0,
    "movieInfo": {}
  },
  "Chupa Chupi (2D - Assamese)": {
    "shows": 5,
    "venues": 5,
    "cities": 4,
    "totalSeats": 855,
    "ticketsSold": 109,
    "occupancy": 12.75,
    "grossRevenue": 19039.88,
    "fastfilling": 0,
    "housefull": 0,
    "movieInfo": {}
  },
  "Bol Radha Bol (2D - Bhojpuri)": {
    "shows": 2,
    "venues": 1,
    "cities": 1,
    "totalSeats": 632,
    "ticketsSold": 0,
    "occupancy": 0.0,
    "grossRevenue": 0.0,
    "fastfilling": 0,
    "housefull": 0,
    "movieInfo": {}
  },
  "Pati Patni Aur Woh Do (2D - Hindi)": {
    "shows": 2,
    "venues": 1,
    "cities": 1,
    "totalSeats": 724,
    "ticketsSold": 2,
    "occupancy": 0.28,
    "grossRevenue": 200.0,
    "fastfilling": 0,
    "housefull": 0,
    "movieInfo": {}
  },
  "Maa Inti Bangaaram (2D - Telugu)": {
    "shows": 7,
    "venues": 5,
    "cities": 5,
    "totalSeats": 2099,
    "ticketsSold": 272,
    "occupancy": 12.96,
    "grossRevenue": 19165.0,
    "fastfilling": 1,
    "housefull": 0,
    "movieInfo": {}
  },
  "Love Oh Love (2D - Telugu)": {
    "shows": 6,
    "venues": 3,
    "cities": 3,
    "totalSeats": 2928,
    "ticketsSold": 105,
    "occupancy": 3.59,
    "grossRevenue": 11635.0,
    "fastfilling": 0,
    "housefull": 0,
    "movieInfo": {}
  },
  "Balan: The Boy (2D - Malayalam)": {
    "shows": 5,
    "venues": 4,
    "cities": 4,
    "totalSeats": 1197,
    "ticketsSold": 237,
    "occupancy": 19.8,
    "grossRevenue": 38935.0,
    "fastfilling": 0,
    "housefull": 0,
    "movieInfo": {}
  },
  "Koka Deuta Nati Aru Hati 2 (2D - Assamese)": {
    "shows": 15,
    "venues": 9,
    "cities": 5,
    "totalSeats": 2197,
    "ticketsSold": 642,
    "occupancy": 29.22,
    "grossRevenue": 121349.88,
    "fastfilling": 4,
    "housefull": 0,
    "movieInfo": {}
  },
  "Kireedam (2D - Malayalam)": {
    "shows": 5,
    "venues": 5,
    "cities": 5,
    "totalSeats": 1127,
    "ticketsSold": 206,
    "occupancy": 18.28,
    "grossRevenue": 36225.0,
    "fastfilling": 0,
    "housefull": 0,
    "movieInfo": {}
  },
  "Bali (2D - Chattisgarhi)": {
    "shows": 2,
    "venues": 1,
    "cities": 1,
    "totalSeats": 1822,
    "ticketsSold": 4,
    "occupancy": 0.22,
    "grossRevenue": 500.0,
    "fastfilling": 0,
    "housefull": 0,
    "movieInfo": {}
  },
  "Moana (IMAX 3D - English)": {
    "shows": 7,
    "venues": 3,
    "cities": 3,
    "totalSeats": 2138,
    "ticketsSold": 210,
    "occupancy": 9.82,
    "grossRevenue": 66995.0,
    "fastfilling": 0,
    "housefull": 0,
    "movieInfo": {}
  },
  "I, Nobody (2D - Tamil)": {
    "shows": 2,
    "venues": 2,
    "cities": 2,
    "totalSeats": 327,
    "ticketsSold": 45,
    "occupancy": 13.76,
    "grossRevenue": 6733.45,
    "fastfilling": 0,
    "housefull": 0,
    "movieInfo": {}
  },
  "Dark (2026) (2D - Tamil)": {
    "shows": 6,
    "venues": 3,
    "cities": 1,
    "totalSeats": 840,
    "ticketsSold": 61,
    "occupancy": 7.26,
    "grossRevenue": 5127.65,
    "fastfilling": 0,
    "housefull": 0,
    "movieInfo": {}
  },
  "Moana (3D - English)": {
    "shows": 19,
    "venues": 16,
    "cities": 9,
    "totalSeats": 2475,
    "ticketsSold": 171,
    "occupancy": 6.91,
    "grossRevenue": 39533.46,
    "fastfilling": 0,
    "housefull": 0,
    "movieInfo": {}
  },
  "Lakshmikanthan Kolai Vazhakku (2D - Tamil)": {
    "shows": 4,
    "venues": 4,
    "cities": 2,
    "totalSeats": 997,
    "ticketsSold": 83,
    "occupancy": 8.32,
    "grossRevenue": 9835.0,
    "fastfilling": 0,
    "housefull": 0,
    "movieInfo": {}
  },
  "Love Oh Love (2D - Tamil)": {
    "shows": 12,
    "venues": 12,
    "cities": 4,
    "totalSeats": 2482,
    "ticketsSold": 226,
    "occupancy": 9.11,
    "grossRevenue": 29721.3,
    "fastfilling": 0,
    "housefull": 0,
    "movieInfo": {}
  },
  "Deool Band 2 (2D - Marathi)": {
    "shows": 2,
    "venues": 2,
    "cities": 2,
    "totalSeats": 452,
    "ticketsSold": 13,
    "occupancy": 2.88,
    "grossRevenue": 2030.0,
    "fastfilling": 0,
    "housefull": 0,
    "movieInfo": {}
  },
  "Idhayam Murali (EPIQ - Tamil)": {
    "shows": 1,
    "venues": 1,
    "cities": 1,
    "totalSeats": 307,
    "ticketsSold": 24,
    "occupancy": 7.82,
    "grossRevenue": 4800.0,
    "fastfilling": 0,
    "housefull": 0,
    "movieInfo": {}
  },
  "Nooru Sami (2D - Tamil)": {
    "shows": 2,
    "venues": 1,
    "cities": 1,
    "totalSeats": 72,
    "ticketsSold": 0,
    "occupancy": 0.0,
    "grossRevenue": 0.0,
    "fastfilling": 0,
    "housefull": 0,
    "movieInfo": {}
  },
  "I, Nobody (2D - Telugu)": {
    "shows": 6,
    "venues": 3,
    "cities": 3,
    "totalSeats": 1862,
    "ticketsSold": 148,
    "occupancy": 7.95,
    "grossRevenue": 16620.0,
    "fastfilling": 0,
    "housefull": 0,
    "movieInfo": {}
  },
  "Baby Do Die Do (2D - Hindi)": {
    "shows": 10,
    "venues": 8,
    "cities": 2,
    "totalSeats": 980,
    "ticketsSold": 156,
    "occupancy": 15.92,
    "grossRevenue": 31146.0,
    "fastfilling": 1,
    "housefull": 0,
    "movieInfo": {}
  },
  "Dhamaal 4 (4DX - Hindi)": {
    "shows": 1,
    "venues": 1,
    "cities": 1,
    "totalSeats": 116,
    "ticketsSold": 67,
    "occupancy": 57.76,
    "grossRevenue": 16750.0,
    "fastfilling": 1,
    "housefull": 0,
    "movieInfo": {}
  },
  "Toy Story 5 (MX4D 3D - Hindi)": {
    "shows": 1,
    "venues": 1,
    "cities": 1,
    "totalSeats": 135,
    "ticketsSold": 35,
    "occupancy": 25.93,
    "grossRevenue": 9415.0,
    "fastfilling": 0,
    "housefull": 0,
    "movieInfo": {}
  },
  "Minions & Monsters (MX4D 3D - Hindi)": {
    "shows": 2,
    "venues": 1,
    "cities": 1,
    "totalSeats": 270,
    "ticketsSold": 75,
    "occupancy": 27.78,
    "grossRevenue": 20175.0,
    "fastfilling": 0,
    "housefull": 0,
    "movieInfo": {}
  },
  "Minions & Monsters (3D - Hindi)": {
    "shows": 2,
    "venues": 2,
    "cities": 2,
    "totalSeats": 335,
    "ticketsSold": 27,
    "occupancy": 8.06,
    "grossRevenue": 3962.0,
    "fastfilling": 0,
    "housefull": 0,
    "movieInfo": {}
  },
  "Moana (2D - Hindi)": {
    "shows": 16,
    "venues": 12,
    "cities": 4,
    "totalSeats": 2716,
    "ticketsSold": 171,
    "occupancy": 6.3,
    "grossRevenue": 21370.0,
    "fastfilling": 0,
    "housefull": 0,
    "movieInfo": {}
  },
  "Kadaknath (2D - Gujarati)": {
    "shows": 5,
    "venues": 3,
    "cities": 2,
    "totalSeats": 484,
    "ticketsSold": 74,
    "occupancy": 15.29,
    "grossRevenue": 11257.0,
    "fastfilling": 0,
    "housefull": 0,
    "movieInfo": {}
  },
  "Rao Bahadur (2D - Telugu)": {
    "shows": 3,
    "venues": 2,
    "cities": 2,
    "totalSeats": 1337,
    "ticketsSold": 300,
    "occupancy": 22.44,
    "grossRevenue": 30000.0,
    "fastfilling": 0,
    "housefull": 0,
    "movieInfo": {}
  },
  "Mother Promise (2D - Kannada)": {
    "shows": 11,
    "venues": 7,
    "cities": 4,
    "totalSeats": 4103,
    "ticketsSold": 184,
    "occupancy": 4.48,
    "grossRevenue": 22525.0,
    "fastfilling": 0,
    "housefull": 0,
    "movieInfo": {}
  },
  "Rakky (2D - Kannada)": {
    "shows": 2,
    "venues": 2,
    "cities": 2,
    "totalSeats": 339,
    "ticketsSold": 37,
    "occupancy": 10.91,
    "grossRevenue": 3430.0,
    "fastfilling": 0,
    "housefull": 0,
    "movieInfo": {}
  },
  "Graamaayana (2D - Kannada)": {
    "shows": 2,
    "venues": 2,
    "cities": 2,
    "totalSeats": 677,
    "ticketsSold": 33,
    "occupancy": 4.87,
    "grossRevenue": 4850.0,
    "fastfilling": 0,
    "housefull": 0,
    "movieInfo": {}
  },
  "Ghabadkund (2D - Marathi)": {
    "shows": 4,
    "venues": 4,
    "cities": 3,
    "totalSeats": 527,
    "ticketsSold": 67,
    "occupancy": 12.71,
    "grossRevenue": 9902.0,
    "fastfilling": 0,
    "housefull": 0,
    "movieInfo": {}
  },
  "Minions & Monsters (3D - English)": {
    "shows": 3,
    "venues": 3,
    "cities": 3,
    "totalSeats": 354,
    "ticketsSold": 41,
    "occupancy": 11.58,
    "grossRevenue": 8584.0,
    "fastfilling": 0,
    "housefull": 0,
    "movieInfo": {}
  },
  "Colony (2D - Korean)": {
    "shows": 1,
    "venues": 1,
    "cities": 1,
    "totalSeats": 75,
    "ticketsSold": 2,
    "occupancy": 2.67,
    "grossRevenue": 500.0,
    "fastfilling": 0,
    "housefull": 0,
    "movieInfo": {}
  },
  "Run (2D - Tamil)": {
    "shows": 3,
    "venues": 2,
    "cities": 2,
    "totalSeats": 706,
    "ticketsSold": 66,
    "occupancy": 9.35,
    "grossRevenue": 9020.0,
    "fastfilling": 0,
    "housefull": 0,
    "movieInfo": {}
  },
  "The Invite (2D - English)": {
    "shows": 1,
    "venues": 1,
    "cities": 1,
    "totalSeats": 56,
    "ticketsSold": 19,
    "occupancy": 33.93,
    "grossRevenue": 9481.0,
    "fastfilling": 0,
    "housefull": 0,
    "movieInfo": {}
  },
  "Moana (4DX 3D - Hindi)": {
    "shows": 2,
    "venues": 2,
    "cities": 2,
    "totalSeats": 236,
    "ticketsSold": 78,
    "occupancy": 33.05,
    "grossRevenue": 19662.0,
    "fastfilling": 1,
    "housefull": 0,
    "movieInfo": {}
  },
  "Krishnavataram Part 1: The Heart (2D - Hindi)": {
    "shows": 2,
    "venues": 1,
    "cities": 1,
    "totalSeats": 135,
    "ticketsSold": 0,
    "occupancy": 0.0,
    "grossRevenue": 0.0,
    "fastfilling": 0,
    "housefull": 0,
    "movieInfo": {}
  },
  "Jindgi Haji Baki Che Dost (2D - Gujarati)": {
    "shows": 8,
    "venues": 4,
    "cities": 1,
    "totalSeats": 849,
    "ticketsSold": 358,
    "occupancy": 42.17,
    "grossRevenue": 33084.0,
    "fastfilling": 1,
    "housefull": 0,
    "movieInfo": {}
  },
  "Minions & Monsters (2D - Hindi)": {
    "shows": 2,
    "venues": 1,
    "cities": 1,
    "totalSeats": 547,
    "ticketsSold": 24,
    "occupancy": 4.39,
    "grossRevenue": 3600.0,
    "fastfilling": 0,
    "housefull": 0,
    "movieInfo": {}
  },
  "Rangaaa (2D - Gujarati)": {
    "shows": 8,
    "venues": 7,
    "cities": 2,
    "totalSeats": 663,
    "ticketsSold": 6,
    "occupancy": 0.9,
    "grossRevenue": 700.0,
    "fastfilling": 0,
    "housefull": 0,
    "movieInfo": {}
  },
  "Moana (2D - English)": {
    "shows": 1,
    "venues": 1,
    "cities": 1,
    "totalSeats": 72,
    "ticketsSold": 0,
    "occupancy": 0.0,
    "grossRevenue": 0.0,
    "fastfilling": 0,
    "housefull": 0,
    "movieInfo": {}
  },
  "Tula Pahta (2D - Marathi)": {
    "shows": 6,
    "venues": 6,
    "cities": 5,
    "totalSeats": 940,
    "ticketsSold": 115,
    "occupancy": 12.23,
    "grossRevenue": 18153.0,
    "fastfilling": 0,
    "housefull": 0,
    "movieInfo": {}
  },
  "Evil Dead Burn (4DX - Hindi)": {
    "shows": 1,
    "venues": 1,
    "cities": 1,
    "totalSeats": 116,
    "ticketsSold": 93,
    "occupancy": 80.17,
    "grossRevenue": 18507.0,
    "fastfilling": 1,
    "housefull": 0,
    "movieInfo": {}
  },
  "Hrudhayam Murali (2D - Telugu)": {
    "shows": 2,
    "venues": 1,
    "cities": 1,
    "totalSeats": 1248,
    "ticketsSold": 626,
    "occupancy": 50.16,
    "grossRevenue": 51750.0,
    "fastfilling": 2,
    "housefull": 0,
    "movieInfo": {}
  },
  "Nevermind (2D - Bengali)": {
    "shows": 2,
    "venues": 1,
    "cities": 1,
    "totalSeats": 200,
    "ticketsSold": 0,
    "occupancy": 0.0,
    "grossRevenue": 0.0,
    "fastfilling": 0,
    "housefull": 0,
    "movieInfo": {}
  },
  "Moana (MX4D 3D - Hindi)": {
    "shows": 1,
    "venues": 1,
    "cities": 1,
    "totalSeats": 135,
    "ticketsSold": 36,
    "occupancy": 26.67,
    "grossRevenue": 9684.0,
    "fastfilling": 0,
    "housefull": 0,
    "movieInfo": {}
  },
  "Toy Story 5 (3D - Hindi)": {
    "shows": 2,
    "venues": 2,
    "cities": 1,
    "totalSeats": 246,
    "ticketsSold": 21,
    "occupancy": 8.54,
    "grossRevenue": 3150.0,
    "fastfilling": 0,
    "housefull": 0,
    "movieInfo": {}
  },
  "Obsession  (2D - English)": {
    "shows": 2,
    "venues": 2,
    "cities": 2,
    "totalSeats": 350,
    "ticketsSold": 30,
    "occupancy": 8.57,
    "grossRevenue": 4994.0,
    "fastfilling": 0,
    "housefull": 0,
    "movieInfo": {}
  },
  "Nagabandham - The Secret Treasure (4DX - Hindi)": {
    "shows": 2,
    "venues": 1,
    "cities": 1,
    "totalSeats": 240,
    "ticketsSold": 68,
    "occupancy": 28.33,
    "grossRevenue": 13532.0,
    "fastfilling": 0,
    "housefull": 0,
    "movieInfo": {}
  },
  "Linebala (2D - Odia)": {
    "shows": 2,
    "venues": 2,
    "cities": 2,
    "totalSeats": 94,
    "ticketsSold": 0,
    "occupancy": 0.0,
    "grossRevenue": 0.0,
    "fastfilling": 0,
    "housefull": 0,
    "movieInfo": {}
  },
  "Mudharkanal (2D - Tamil)": {
    "shows": 2,
    "venues": 1,
    "cities": 1,
    "totalSeats": 342,
    "ticketsSold": 27,
    "occupancy": 7.89,
    "grossRevenue": 4050.0,
    "fastfilling": 0,
    "housefull": 0,
    "movieInfo": {}
  },
  "Putham Pudhu Neram (2D - Tamil)": {
    "shows": 1,
    "venues": 1,
    "cities": 1,
    "totalSeats": 138,
    "ticketsSold": 0,
    "occupancy": 0.0,
    "grossRevenue": 0.0,
    "fastfilling": 0,
    "housefull": 0,
    "movieInfo": {}
  },
  "Tumbadchi Manjula (2D - Marathi)": {
    "shows": 1,
    "venues": 1,
    "cities": 1,
    "totalSeats": 187,
    "ticketsSold": 30,
    "occupancy": 16.04,
    "grossRevenue": 4620.0,
    "fastfilling": 0,
    "housefull": 0,
    "movieInfo": {}
  },
  "Aroopi (Tamil) (2D - Tamil)": {
    "shows": 1,
    "venues": 1,
    "cities": 1,
    "totalSeats": 158,
    "ticketsSold": 7,
    "occupancy": 4.43,
    "grossRevenue": 1030.0,
    "fastfilling": 0,
    "housefull": 0,
    "movieInfo": {}
  },
  "Gatta Kusthi 2 (EPIQ - Tamil)": {
    "shows": 1,
    "venues": 1,
    "cities": 1,
    "totalSeats": 307,
    "ticketsSold": 14,
    "occupancy": 4.56,
    "grossRevenue": 2800.0,
    "fastfilling": 0,
    "housefull": 0,
    "movieInfo": {}
  },
  "Toy Story 5 (3D - English)": {
    "shows": 1,
    "venues": 1,
    "cities": 1,
    "totalSeats": 189,
    "ticketsSold": 0,
    "occupancy": 0.0,
    "grossRevenue": 0.0,
    "fastfilling": 0,
    "housefull": 0,
    "movieInfo": {}
  }
}